snap_business_sdk/__init__.py
snap_business_sdk/api_client.py
snap_business_sdk/capi_utils.py
snap_business_sdk/configuration.py
snap_business_sdk/exceptions.py
snap_business_sdk/model_utils.py
snap_business_sdk/rest.py
snap_business_sdk/api/__init__.py
snap_business_sdk/api/default_api.py
snap_business_sdk/apis/__init__.py
snap_business_sdk/docs/CapiEvent.md
snap_business_sdk/docs/DefaultApi.md
snap_business_sdk/docs/Response.md
snap_business_sdk/docs/ResponseErrorRecords.md
snap_business_sdk/model/__init__.py
snap_business_sdk/model/capi_event.py
snap_business_sdk/model/response.py
snap_business_sdk/model/response_error_records.py
snap_business_sdk/model/response_logs.py
snap_business_sdk/model/response_logs_log.py
snap_business_sdk/model/response_stats.py
snap_business_sdk/model/response_stats_data.py
snap_business_sdk/model/response_stats_test.py
snap_business_sdk/model/test_response.py
snap_business_sdk/model/validated_fields.py
snap_business_sdk/model/validated_fields_items.py
snap_business_sdk/models/__init__.py
snap_business_sdk/public/__init__.py
snap_business_sdk/public/conversion_api.py
snap_business_sdk/public/conversion_event.py
snap_business_sdk/test/__init__.py
snap_business_sdk/test/test_capi_event.py
snap_business_sdk/test/test_default_api.py
snap_business_sdk/test/test_response.py
snap_business_sdk/test/test_response_error_records.py
snap_business_sdk-1.0.0.dist-info/METADATA
snap_business_sdk-1.0.0.dist-info/WHEEL
snap_business_sdk-1.0.0.dist-info/licenses/LICENSE
snap_business_sdk-1.0.0.dist-info/RECORD
