Metadata-Version: 2.1
Name: snap_business_sdk
Version: 1.0.0
Summary: Python Business SDK for Snap Conversions API
Project-URL: Homepage, https://github.com/Snapchat/business-sdk-python
Project-URL: Bug Tracker, https://github.com/Snapchat/business-sdk-python/issues
Author-email: Snapchat Attribution Team <attribution-team@snapchat.com>
License-File: LICENSE
Classifier: Operating System :: OS Independent
Classifier: Programming Language :: Python :: 3
Requires-Python: >=3.7
Requires-Dist: jellyfish
Requires-Dist: python-dateutil
Requires-Dist: urllib3>=1.25.3
